parse_reparsepoint/Interpreter.py
parse_reparsepoint/Navigator.py
parse_reparsepoint/__init__.py
parse_reparsepoint/__main__.py
parse_reparsepoint-0.1.0.dist-info/LICENSE
parse_reparsepoint-0.1.0.dist-info/METADATA
parse_reparsepoint-0.1.0.dist-info/WHEEL
parse_reparsepoint-0.1.0.dist-info/entry_points.txt
parse_reparsepoint-0.1.0.dist-info/top_level.txt
parse_reparsepoint-0.1.0.dist-info/RECORD
