Metadata-Version: 2.1
Name: parse-reparsepoint
Version: 0.1.0
Summary: Parse NTFS reparse points
Author-email: Jeremy Dunn <jeremy.dunn315@gmail.com>
License: GNU GENERAL PUBLIC LICENSE
Project-URL: homepage, https://github.com/stolenfootball/parse-reparsepoint
Keywords: ntfs,reparse point,parse,reparsepoint,onedrive
Classifier: Development Status :: 3 - Alpha
Classifier: Intended Audience :: Developers
Classifier: License :: OSI Approved :: GNU General Public License v3 or later (GPLv3+)
Classifier: Programming Language :: Python :: 3
Classifier: Programming Language :: Python
Requires-Python: >=3.6.0
License-File: LICENSE
Requires-Dist: argparse
Requires-Dist: typing
Provides-Extra: dev
Requires-Dist: black ; extra == 'dev'
Requires-Dist: bumpver ; extra == 'dev'
Requires-Dist: isort ; extra == 'dev'
Requires-Dist: pip-tools ; extra == 'dev'
Requires-Dist: flake8 ; extra == 'dev'
